{
    "tag_name": "v0.2.18.Final",
    "author": {
        "gists_url": "https://api.github.com/users/EricWittmann/gists{/gist_id}",
        "repos_url": "https://api.github.com/users/EricWittmann/repos",
        "following_url": "https://api.github.com/users/EricWittmann/following{/other_user}",
        "starred_url": "https://api.github.com/users/EricWittmann/starred{/owner}{/repo}",
        "login": "EricWittmann",
        "followers_url": "https://api.github.com/users/EricWittmann/followers",
        "type": "User",
        "url": "https://api.github.com/users/EricWittmann",
        "subscriptions_url": "https://api.github.com/users/EricWittmann/subscriptions",
        "received_events_url": "https://api.github.com/users/EricWittmann/received_events",
        "avatar_url": "https://avatars2.githubusercontent.com/u/1890703?v=4",
        "events_url": "https://api.github.com/users/EricWittmann/events{/privacy}",
        "html_url": "https://github.com/EricWittmann",
        "site_admin": false,
        "id": 1890703,
        "gravatar_id": "",
        "node_id": "MDQ6VXNlcjE4OTA3MDM=",
        "organizations_url": "https://api.github.com/users/EricWittmann/orgs"
    },
    "created_at": "2018-10-31T17:46:40Z",
    "body": "This represents the official release of Apicurio Studio, version 0.2.18.Final.\n\nThe following issues have been resolved in this release:\n\n* [#483](https://github.com/Apicurio/apicurio-studio/issues/483) Editor: Required properties deleted from Data Types still referenced in downloaded YAML\n* [#482](https://github.com/Apicurio/apicurio-studio/issues/482) Security Schemes : None and another one (Apikey, Bearer...) in same time\n* [#480](https://github.com/Apicurio/apicurio-studio/issues/480) Editor: Update the L&F of the Add Property dialog to use the new full-screen editor approach\n* [#479](https://github.com/Apicurio/apicurio-studio/issues/479) Editor: Update L&F of Title Editor - use ✔/✘ buttons instead of Save/Cancel\n* [#478](https://github.com/Apicurio/apicurio-studio/issues/478) Code Editor: ESC and Ctrl-Enter don't work in Chrome\n* [#423](https://github.com/Apicurio/apicurio-studio/issues/423) Editor: Cancel in \"Add property\"-Popup works only on second click when the Name box is empty\n* [#329](https://github.com/Apicurio/apicurio-studio/issues/329) UX: Update the \"lost connection\" dialog in the editor\n* [#283](https://github.com/Apicurio/apicurio-studio/issues/283) Feature: Create New API from template\n* [#140](https://github.com/Apicurio/apicurio-studio/issues/140) Editor: Add UI support for Enums in schema properties\n\n\nFor more information, please see the Apicurio Studio's official project site:\n\n* [General Information](http://www.apicur.io/)\n* [Download/Quickstart](http://www.apicur.io/download)\n* [Blog](http://www.apicur.io/blog)\n",
    "url": "https://api.github.com/repos/Apicurio/apicurio-studio/releases/13761910",
    "assets_url": "https://api.github.com/repos/Apicurio/apicurio-studio/releases/13761910/assets",
    "assets": [
        {
            "created_at": "2018-10-31T17:56:44Z",
            "browser_download_url": "https://github.com/Apicurio/apicurio-studio/releases/download/v0.2.18.Final/apicurio-studio-0.2.18.Final-quickstart.zip",
            "label": "",
            "url": "https://api.github.com/repos/Apicurio/apicurio-studio/releases/assets/9495756",
            "download_count": 0,
            "content_type": "application/zip",
            "size": 169488423,
            "updated_at": "2018-10-31T17:58:46Z",
            "uploader": {
                "gists_url": "https://api.github.com/users/EricWittmann/gists{/gist_id}",
                "repos_url": "https://api.github.com/users/EricWittmann/repos",
                "following_url": "https://api.github.com/users/EricWittmann/following{/other_user}",
                "starred_url": "https://api.github.com/users/EricWittmann/starred{/owner}{/repo}",
                "login": "EricWittmann",
                "followers_url": "https://api.github.com/users/EricWittmann/followers",
                "type": "User",
                "url": "https://api.github.com/users/EricWittmann",
                "subscriptions_url": "https://api.github.com/users/EricWittmann/subscriptions",
                "received_events_url": "https://api.github.com/users/EricWittmann/received_events",
                "avatar_url": "https://avatars2.githubusercontent.com/u/1890703?v=4",
                "events_url": "https://api.github.com/users/EricWittmann/events{/privacy}",
                "html_url": "https://github.com/EricWittmann",
                "site_admin": false,
                "id": 1890703,
                "gravatar_id": "",
                "node_id": "MDQ6VXNlcjE4OTA3MDM=",
                "organizations_url": "https://api.github.com/users/EricWittmann/orgs"
            },
            "name": "apicurio-studio-0.2.18.Final-quickstart.zip",
            "id": 9495756,
            "state": "uploaded",
            "node_id": "MDEyOlJlbGVhc2VBc3NldDk0OTU3NTY="
        },
        {
            "created_at": "2018-10-31T17:58:47Z",
            "browser_download_url": "https://github.com/Apicurio/apicurio-studio/releases/download/v0.2.18.Final/apicurio-studio-0.2.18.Final-quickstart.zip.asc",
            "label": "",
            "url": "https://api.github.com/repos/Apicurio/apicurio-studio/releases/assets/9495782",
            "download_count": 0,
            "content_type": "text/plain",
            "size": 490,
            "updated_at": "2018-10-31T17:58:47Z",
            "uploader": {
                "gists_url": "https://api.github.com/users/EricWittmann/gists{/gist_id}",
                "repos_url": "https://api.github.com/users/EricWittmann/repos",
                "following_url": "https://api.github.com/users/EricWittmann/following{/other_user}",
                "starred_url": "https://api.github.com/users/EricWittmann/starred{/owner}{/repo}",
                "login": "EricWittmann",
                "followers_url": "https://api.github.com/users/EricWittmann/followers",
                "type": "User",
                "url": "https://api.github.com/users/EricWittmann",
                "subscriptions_url": "https://api.github.com/users/EricWittmann/subscriptions",
                "received_events_url": "https://api.github.com/users/EricWittmann/received_events",
                "avatar_url": "https://avatars2.githubusercontent.com/u/1890703?v=4",
                "events_url": "https://api.github.com/users/EricWittmann/events{/privacy}",
                "html_url": "https://github.com/EricWittmann",
                "site_admin": false,
                "id": 1890703,
                "gravatar_id": "",
                "node_id": "MDQ6VXNlcjE4OTA3MDM=",
                "organizations_url": "https://api.github.com/users/EricWittmann/orgs"
            },
            "name": "apicurio-studio-0.2.18.Final-quickstart.zip.asc",
            "id": 9495782,
            "state": "uploaded",
            "node_id": "MDEyOlJlbGVhc2VBc3NldDk0OTU3ODI="
        }
    ],
    "prerelease": false,
    "html_url": "https://github.com/Apicurio/apicurio-studio/releases/tag/v0.2.18.Final",
    "target_commitish": "master",
    "draft": false,
    "zipball_url": "https://api.github.com/repos/Apicurio/apicurio-studio/zipball/v0.2.18.Final",
    "name": "Beta 2.18",
    "upload_url": "https://uploads.github.com/repos/Apicurio/apicurio-studio/releases/13761910/assets{?name,label}",
    "id": 13761910,
    "published_at": "2018-10-31T17:56:44Z",
    "tarball_url": "https://api.github.com/repos/Apicurio/apicurio-studio/tarball/v0.2.18.Final",
    "node_id": "MDc6UmVsZWFzZTEzNzYxOTEw"
}